ksink/__init__.py
ksink/bs4.py
ksink/csv.py
ksink/file.py
ksink/list.py
ksink/lxml.py
ksink/selenium.py
ksink/string.py
ksink-0.0.1.dist-info/LICENSE
ksink-0.0.1.dist-info/METADATA
ksink-0.0.1.dist-info/WHEEL
ksink-0.0.1.dist-info/top_level.txt
ksink-0.0.1.dist-info/RECORD
