Metadata-Version: 2.1
Name: ksink
Version: 0.0.1
Summary: Miscellaneous Python helper functions
Home-page: https://github.com/sitebolts/ksink
Author: SiteBolts
Author-email: admin@sitebolts.com
License: UNKNOWN
Project-URL: Bug Tracker, https://github.com/sitebolts/ksink/issues
Platform: UNKNOWN
Classifier: Programming Language :: Python :: 3
Classifier: License :: OSI Approved :: MIT License
Classifier: Operating System :: OS Independent
Requires-Python: >=3.6
